daiquiri/__init__.py
daiquiri/formatter.py
daiquiri/handlers.py
daiquiri/output.py
daiquiri/py.typed
daiquiri/types.py
daiquiri/tests/__init__.py
daiquiri/tests/test_daiquiri.py
daiquiri/tests/test_formatter.py
daiquiri/tests/test_output.py
daiquiri-3.4.0.dist-info/licenses/LICENSE
daiquiri-3.4.0.dist-info/METADATA
daiquiri-3.4.0.dist-info/WHEEL
daiquiri-3.4.0.dist-info/top_level.txt
daiquiri-3.4.0.dist-info/RECORD
