Metadata-Version: 2.4
Name: daiquiri
Version: 3.4.0
Summary: Library to configure Python logging easily
Author-email: Julien Danjou <julien@danjou.info>
License: Apache 2.0
Project-URL: homepage, https://github.com/Mergifyio/daiquiri
Classifier: Intended Audience :: Information Technology
Classifier: Intended Audience :: System Administrators
Classifier: License :: OSI Approved :: Apache Software License
Classifier: Operating System :: POSIX :: Linux
Classifier: Programming Language :: Python
Classifier: Programming Language :: Python :: 3
Classifier: Programming Language :: Python :: 3.10
Classifier: Programming Language :: Python :: 3.11
Classifier: Programming Language :: Python :: 3.12
Classifier: Programming Language :: Python :: 3.13
Requires-Python: >=3.10
License-File: LICENSE
Requires-Dist: python-json-logger>=3
Provides-Extra: test
Requires-Dist: pytest; extra == "test"
Provides-Extra: systemd
Requires-Dist: systemd-python>=234; extra == "systemd"
Dynamic: license-file
